DEWPython/DEWEquations.py
DEWPython/DEWModel.py
DEWPython/__init__.py
DEWPython/dpronsbl.dat
DEWPython/resources/SUPCRTBL.exe
DEWPython/resources/Wat_den.csv
DEWPython/resources/Xtend.con
DEWPython/resources/aqueousLst.txt
DEWPython/resources/dielectric.csv
DEWPython/resources/dpronsbl.dat
DEWPython/resources/dpronshp.dat
DEWPython/resources/extendMineralDictionary.txt
DEWPython/resources/gasLst.txt
DEWPython/resources/input.csv
DEWPython/resources/mineralDictionary.txt
DEWPython/resources/realReac.con
DEWPython/resources/supcrt96.exe
DEWPython/resources/updateSlop1.dat
DEWPython/resources/water_gibbs.csv
DEWPython-2.0.0.dist-info/LICENSE.txt
DEWPython-2.0.0.dist-info/METADATA
DEWPython-2.0.0.dist-info/WHEEL
DEWPython-2.0.0.dist-info/top_level.txt
DEWPython-2.0.0.dist-info/RECORD
