Metadata-Version: 2.1
Name: DEWPython
Version: 2.0.0
Summary: Python-Implemented Deep Earth Water Model
Home-page: https://github.com/chandr3w/DEWPython
Author: chandr3w
Author-email: amchan@caltech.edu
License: UNKNOWN
Download-URL: https://github.com/chandr3w/DEWPython/archive/2.0.0.tar.gz
Platform: UNKNOWN
Classifier: Programming Language :: Python :: 3.7
Classifier: License :: OSI Approved :: GNU General Public License v3 (GPLv3)
Classifier: Operating System :: OS Independent
Requires-Dist: numpy
Requires-Dist: pandas
Requires-Dist: matplotlib
